wwpdb/utils/seqdb_v2/BlastProcess.py
wwpdb/utils/seqdb_v2/FastaUtil.py
wwpdb/utils/seqdb_v2/FetchNcbiXml.py
wwpdb/utils/seqdb_v2/FetchUniProtEntry.py
wwpdb/utils/seqdb_v2/FetchUnpXml.py
wwpdb/utils/seqdb_v2/NcbiBlastService.py
wwpdb/utils/seqdb_v2/ReadNcbiBlastXml.py
wwpdb/utils/seqdb_v2/ReadNcbiSummary.py
wwpdb/utils/seqdb_v2/ReadNcbiXml.py
wwpdb/utils/seqdb_v2/ReadUnpBlastXml.py
wwpdb/utils/seqdb_v2/ReadUnpXml.py
wwpdb/utils/seqdb_v2/UnpBlastService.py
wwpdb/utils/seqdb_v2/__init__.py
wwpdb/utils/seqdb_v2/mmCIFUtil.py
wwpdb_utils_seqdb_v2-0.14.dist-info/METADATA
wwpdb_utils_seqdb_v2-0.14.dist-info/WHEEL
wwpdb_utils_seqdb_v2-0.14.dist-info/RECORD
