Metadata-Version: 2.4
Name: wwpdb.utils.seqdb-v2
Version: 0.14
Summary: wwPDB Sequence search utilities
Project-URL: Homepage, https://github.com/rcsb/py-wwpdb_utils_seqdb_v2
Author-email: Ezra Peisach <ezra.peisach@rcsb.org>
License-Expression: Apache-2.0
Classifier: Development Status :: 3 - Alpha
Classifier: Intended Audience :: Developers
Classifier: License :: OSI Approved :: Apache Software License
Classifier: Natural Language :: English
Classifier: Programming Language :: Python
Classifier: Programming Language :: Python :: 3
Classifier: Programming Language :: Python :: 3.6
Classifier: Programming Language :: Python :: 3.7
Classifier: Programming Language :: Python :: 3.8
Classifier: Programming Language :: Python :: 3.9
Requires-Python: >=3.6
Requires-Dist: mmcif
Requires-Dist: mmcif-utils
Requires-Dist: requests
Requires-Dist: wwpdb-utils-config>=0.33
